README.md
setup.py
async_repeat/__init__.py
async_repeat/core.py
async_repeat.egg-info/PKG-INFO
async_repeat.egg-info/SOURCES.txt
async_repeat.egg-info/dependency_links.txt
async_repeat.egg-info/top_level.txt