Metadata-Version: 2.1
Name: async-repeat
Version: 0.0.1
Summary: A simple async function repeater
Home-page: UNKNOWN
Author: George Miao
Author-email: ge@georgemiao.com
License: UNKNOWN
Platform: UNKNOWN
Classifier: Programming Language :: Python :: 3
Classifier: License :: OSI Approved :: MIT License
Classifier: Operating System :: OS Independent
Requires-Python: >=3.6
